aplicacion_ventas/__init__.py
aplicacion_ventas/descuentos.py
aplicacion_ventas/exceptions.py
aplicacion_ventas/gestor_ventas.py
aplicacion_ventas/impuestos.py
aplicacion_ventas/precios.py
aplicacion_ventas_gutierrez-1.0.1.dist-info/licenses/LICENSE
tests/__init__.py
tests/test_aplicacion_ventas.py
aplicacion_ventas_gutierrez-1.0.1.dist-info/METADATA
aplicacion_ventas_gutierrez-1.0.1.dist-info/WHEEL
aplicacion_ventas_gutierrez-1.0.1.dist-info/top_level.txt
aplicacion_ventas_gutierrez-1.0.1.dist-info/RECORD
